ceit_simupy/__init__.py
ceit_simupy/main.py
ceit_simupy/data/anom/Info_15_minutos.txt
ceit_simupy/data/anom/Info_laboratorio.txt
ceit_simupy/data/norm/Info_15_minutos.txt
ceit_simupy/data/norm/Info_laboratorio.txt
ceit_simupy-0.0.11.dist-info/LICENSE
ceit_simupy-0.0.11.dist-info/METADATA
ceit_simupy-0.0.11.dist-info/WHEEL
ceit_simupy-0.0.11.dist-info/top_level.txt
ceit_simupy-0.0.11.dist-info/RECORD
