Metadata-Version: 2.1
Name: ceit-simupy
Version: 0.0.11
Summary: A small package for an easier use of our Simulink tool
Author: Aitor Domec
Author-email: adomec@ceit.es
Classifier: Programming Language :: Python :: 3
Classifier: License :: OSI Approved :: MIT License
Classifier: Operating System :: OS Independent
License-File: LICENSE
Requires-Dist: setuptools
Requires-Dist: pandas
